icij_worker/__init__.py
icij_worker/__main__.py
icij_worker/app.py
icij_worker/constants.py
icij_worker/exceptions.py
icij_worker/objects.py
icij_worker/routing_strategy.py
icij_worker/typing_.py
icij_worker/backend/__init__.py
icij_worker/backend/backend.py
icij_worker/backend/mp.py
icij_worker/cli/__init__.py
icij_worker/cli/tasks.py
icij_worker/cli/utils.py
icij_worker/cli/workers.py
icij_worker/event_publisher/__init__.py
icij_worker/event_publisher/amqp.py
icij_worker/event_publisher/event_publisher.py
icij_worker/event_publisher/neo4j_.py
icij_worker/http_/__init__.py
icij_worker/http_/config.py
icij_worker/http_/constants.py
icij_worker/http_/dependencies.py
icij_worker/http_/main.py
icij_worker/http_/objects.py
icij_worker/http_/run.py
icij_worker/http_/service.py
icij_worker/http_/task_client.py
icij_worker/http_/tasks.py
icij_worker/task_manager/__init__.py
icij_worker/task_manager/amqp.py
icij_worker/task_manager/neo4j_.py
icij_worker/task_storage/__init__.py
icij_worker/task_storage/fs.py
icij_worker/task_storage/key_value.py
icij_worker/task_storage/neo4j_.py
icij_worker/task_storage/postgres/__init__.py
icij_worker/task_storage/postgres/connection_info.py
icij_worker/task_storage/postgres/db_mate.py
icij_worker/task_storage/postgres/postgres.py
icij_worker/task_storage/postgres/db/schema.sql
icij_worker/task_storage/postgres/db/migrations/20240802104314_add_tasks_support.sql
icij_worker/task_storage/postgres/db/migrations/20240827142011_rename_task_arguments_into_args.sql
icij_worker/task_storage/postgres/db/migrations/20240919114022_rename_namespace_into_group.sql
icij_worker/task_storage/postgres/db/migrations/20250114171324_remove_task_cancelled_at.sql
icij_worker/task_storage/postgres/db/migrations/20250115170559_rename_task_group_into_group_id.sql
icij_worker/utils/__init__.py
icij_worker/utils/amqp.py
icij_worker/utils/asyncio_.py
icij_worker/utils/dependencies.py
icij_worker/utils/http.py
icij_worker/utils/logging_.py
icij_worker-0.18.2.dist-info/METADATA
icij_worker-0.18.2.dist-info/WHEEL
icij_worker-0.18.2.dist-info/entry_points.txt
icij_worker-0.18.2.dist-info/RECORD
