Metadata-Version: 2.4
Name: icij-worker
Version: 0.18.2
Summary: Create asynchronous tasks from Python functions
Project-URL: Repository, https://github.com/ICIJ/icij-python
Project-URL: Issues, https://github.com/ICIJ/icij-python/issues
Author-email: Clément Doumouro <cdoumouro@icij.org>, ICIJ <engineering@icij.org>
Requires-Python: ~=3.10
Requires-Dist: alive-progress>=3.2.0
Requires-Dist: icij-common~=0.7.2
Requires-Dist: typer<0.14,>=0.12.5
Requires-Dist: typing-extensions~=4.12.2
Provides-Extra: amqp
Requires-Dist: aio-pika~=9.4; extra == 'amqp'
Requires-Dist: aiohttp~=3.9; extra == 'amqp'
Provides-Extra: fs
Requires-Dist: sqlitedict~=2.1; extra == 'fs'
Requires-Dist: ujson~=5.10; extra == 'fs'
Provides-Extra: http
Requires-Dist: aiohttp~=3.9; extra == 'http'
Requires-Dist: fastapi[standard]~=0.115; extra == 'http'
Requires-Dist: uvicorn>=0.34.0; extra == 'http'
Provides-Extra: neo4j
Requires-Dist: neo4j~=5.0; extra == 'neo4j'
Provides-Extra: postgres
Requires-Dist: psycopg[binary,pool]~=3.2; extra == 'postgres'
Requires-Dist: sqlitedict~=2.1; extra == 'postgres'
Requires-Dist: ujson~=5.10; extra == 'postgres'
